README.md
setup.py
python_ssp.egg-info/PKG-INFO
python_ssp.egg-info/SOURCES.txt
python_ssp.egg-info/dependency_links.txt
python_ssp.egg-info/requires.txt
python_ssp.egg-info/top_level.txt
ssp/__init__.py
ssp/api.py
ssp/control.py
ssp/securityplan.py